libsbml/_libsbml.cpython-311-darwin.so
libsbml/__init__.py
python_libsbml_experimental-5.21.0.dist-info/RECORD
python_libsbml_experimental-5.21.0.dist-info/WHEEL
python_libsbml_experimental-5.21.0.dist-info/top_level.txt
python_libsbml_experimental-5.21.0.dist-info/METADATA
python_libsbml_experimental-5.21.0.dist-info/licenses/LICENSE.html
python_libsbml_experimental-5.21.0.dist-info/licenses/LICENSE.txt
